{
  "loginWindow": {
    "submit": "Submit",
    "username": "Username",
    "password": "Password",
    "inputUsername":"Input your username here...",
    "inputPassword": "Input your password here..."
  },

  "loginErrors": {
    "usernameErrorLength": "Username must be at least 6 characters",
    "passwordErrorIntro": "Password must contain:",
    "passwordErrorUpper": "At least one upper case English letter,",
    "passwordErrorLower": "At least one lower case English letter,",
    "passwordErrorDigit": "At least one digit,",
    "passwordErrorSpecial": "At least one special character,",
    "passwordErrorLength": "Minimum of six characters"

  },

  "header": {
    "login":"Login",
    "content":"Content",
    "title":"JBugs",
    "language": "Language",
    "bugs": "Bugs",
    "users": "Users",
    "logout": "Logout",
    "profile": "Profile",
    "manage": "Manager",
    "roles_and_permissions": "Roles and Permissions"
  },

  "profileWindow": {
    "welcome": "Welcome",
    "personalInfo": "Personal Information",
    "firstName": "First Name",
    "lastName": "Last Name",
    "email": "Email",
    "phone": "Phone Number"
  },

  "addBug": {
    "title": "Title",
    "inputTitle": "Input title here...",
    "description": "Description",
    "inputDescription": "Input the description here...",
    "version": "Version",
    "inputVersion": "Input the version here...",
    "fixedVersion": "Fixed Version",
    "inputFixedVersion": "Input the fixed version here...",
    "targetDate": "Target Date",
    "severity": "Severity",
    "CRITICAL": "CRITICAL",
    "HIGH": "HIGH",
    "MEDIUM": "MEDIUM",
    "LOW": "LOW",
    "assignedTo": "Assigned",
    "inputAssignedTo": "Input the name here...",
    "buttonAddBug": "Add Bug"

  },

  "bugPopup": {
    "description": "Descriprion",
    "exportPdf": "Export to Pdf"
  },

  "bugList": {
    "number": "#",
    "title": "Title",
    "version": "Version",
    "targetDate": "Target Date",
    "status": "Status",
    "fixedVersion": "Fixed Version",
    "severity": "Severity",
    "createdBy": "Created By User",
    "assignedTo": "Assigned To",
    "exportExcel": "Export Excel"
  }
}